rpyc_import_bridge/__init__.py
rpyc_import_bridge/debug.py
rpyc_import_bridge/import_bridge.py
rpyc_import_bridge/proxy_generator.py
rpyc_import_bridge/util.py
rpyc_import_bridge-0.1.1.dist-info/METADATA
rpyc_import_bridge-0.1.1.dist-info/WHEEL
rpyc_import_bridge-0.1.1.dist-info/RECORD
