Metadata-Version: 2.4
Name: rpyc-import-bridge
Version: 0.1.1
Summary: import proxying for rpyc
Author-email: Red Thing <redthing1@alt.icu>
Requires-Python: >=3.11
Requires-Dist: rpyc>=6.0.2
